<?xml version="1.0"?>
<object name="portal_skins">
 <object name="cpsportlets_default" meta_type="Filesystem Directory View"
    directory="CPSPortlets/skins/cpsportlets_default"/>
 <object name="cpsportlets_layouts" meta_type="Filesystem Directory View"
    directory="CPSPortlets/skins/cpsportlets_layouts"/>
 <object name="cpsportlets_schemas" meta_type="Filesystem Directory View"
    directory="CPSPortlets/skins/cpsportlets_schemas"/>
 <object name="cpsportlets_types" meta_type="Filesystem Directory View"
    directory="CPSPortlets/skins/cpsportlets_vocabularies"/>
 <object name="cpsportlets_vocabularies" meta_type="Filesystem Directory View"
    directory="CPSPortlets/skins/cpsportlets_types"/>
 <object name="cpsportlets_widgets" meta_type="Filesystem Directory View"
    directory="CPSPortlets/skins/cpsportlets_widgets"/>
 <skin-path name="CPSSkins">
  <layer name="cpsportlets_default" insert-after="custom"/>
  <layer name="cpsportlets_widgets" insert-after="custom"/>
 </skin-path>
 <skin-path name="CPSSkins-macroless">
  <layer name="cpsportlets_schemas" insert-after="custom"/>
  <layer name="cpsportlets_vocabularies" insert-after="custom"/>
  <layer name="cpsportlets_layouts" insert-after="custom"/>
  <layer name="cpsportlets_widgets" insert-after="custom"/>
  <layer name="cpsportlets_default" insert-after="custom"/>
  <layer name="cpsportlets_types" insert-after="custom"/>
 </skin-path>
</object>
